CHANGES.rst
CONTRIBUTORS.rst
MANIFEST.in
Makefile
README.rst
requirements-4.3.txt
requirements-5.2.txt
requirements-6.0.txt
setup.cfg
setup.py
docs/LICENSE.GPL
docs/LICENSE.rst
docs/index.rst
src/collective/__init__.py
src/collective.behavior.internalnumber.egg-info/PKG-INFO
src/collective.behavior.internalnumber.egg-info/SOURCES.txt
src/collective.behavior.internalnumber.egg-info/dependency_links.txt
src/collective.behavior.internalnumber.egg-info/entry_points.txt
src/collective.behavior.internalnumber.egg-info/namespace_packages.txt
src/collective.behavior.internalnumber.egg-info/not-zip-safe
src/collective.behavior.internalnumber.egg-info/requires.txt
src/collective.behavior.internalnumber.egg-info/top_level.txt
src/collective/behavior/__init__.py
src/collective/behavior/internalnumber/__init__.py
src/collective/behavior/internalnumber/adapters.py
src/collective/behavior/internalnumber/behavior.py
src/collective/behavior/internalnumber/configure.zcml
src/collective/behavior/internalnumber/interfaces.py
src/collective/behavior/internalnumber/setuphandlers.py
src/collective/behavior/internalnumber/subscribers.py
src/collective/behavior/internalnumber/testing.py
src/collective/behavior/internalnumber/testing.zcml
src/collective/behavior/internalnumber/upgrades.py
src/collective/behavior/internalnumber/browser/__init__.py
src/collective/behavior/internalnumber/browser/configure.zcml
src/collective/behavior/internalnumber/browser/settings.py
src/collective/behavior/internalnumber/browser/static/.gitkeep
src/collective/behavior/internalnumber/locales/collective.behavior.internalnumber.pot
src/collective/behavior/internalnumber/locales/update.sh
src/collective/behavior/internalnumber/locales/fr/LC_MESSAGES/collective.behavior.internalnumber.po
src/collective/behavior/internalnumber/profiles/default/browserlayer.xml
src/collective/behavior/internalnumber/profiles/default/catalog.xml
src/collective/behavior/internalnumber/profiles/default/controlpanel.xml
src/collective/behavior/internalnumber/profiles/default/metadata.xml
src/collective/behavior/internalnumber/profiles/default/registry.xml
src/collective/behavior/internalnumber/profiles/testing/metadata.xml
src/collective/behavior/internalnumber/profiles/testing/types.xml
src/collective/behavior/internalnumber/profiles/testing/types/testtype.xml
src/collective/behavior/internalnumber/profiles/uninstall/browserlayer.xml
src/collective/behavior/internalnumber/profiles/uninstall/catalog.xml
